Tare/__init__.py
Tare/generation/Dataset.py
Tare/generation/ScheduledOptim.py
Tare/generation/Searchnode.py
Tare/generation/Searchnode1.py
Tare/generation/__init__.py
Tare/generation/addtype.py
Tare/generation/parse_dfg.py
Tare/generation/run.py
Tare/generation/runqfix.py
Tare/generation/runtotal.py
Tare/generation/runtotal1.py
Tare/generation/runtotalqfix.py
Tare/generation/solvetree.py
Tare/generation/stringfycode.py
Tare/generation/temp.json
Tare/generation/testDataset.py
Tare/generation/testDefect4j.py
Tare/generation/testDefect4j1.py
Tare/generation/testDefects4jv2.py
Tare/generation/testQuixbug.py
Tare/generation/vocab.py
Tare/model/Attention.py
Tare/model/CombinationLayer.py
Tare/model/ConvolutionForward.py
Tare/model/DenseLayer.py
Tare/model/Embedding.py
Tare/model/LayerNorm.py
Tare/model/Model.py
Tare/model/Multihead_Attention.py
Tare/model/Multihead_Combination.py
Tare/model/SubLayerConnection.py
Tare/model/TokenEmbedding.py
Tare/model/Transfomer.py
Tare/model/TreeConv.py
Tare/model/TreeConvGen.py
Tare/model/__init__.py
Tare/model/blcDP.py
Tare/model/decodeTrans.py
Tare/model/gcnn.py
Tare/model/gcnnnormal.py
Tare/model/gelu.py
Tare/model/graphTransformer.py
Tare/model/postionEmbedding.py
Tare/model/relAttention.py
Tare/model/rightnTransfomer.py
Tare/train/Dataset.py
Tare/train/ScheduledOptim.py
Tare/train/Searchnode.py
Tare/train/__init__.py
Tare/train/blcDP.py
Tare/train/parse_dataflow.py
Tare/train/parse_dfg.py
Tare/train/pretrainDataset.py
Tare/train/run.py
Tare/train/split.py
Tare/train/stringfycode.py
Tare/train/vocab.py
Tare/validation/Searchnode.py
Tare/validation/__init__.py
Tare/validation/repair.py
Tare/validation/repair1.py
Tare/validation/repair2.py
Tare/validation/repairforidx.py
Tare/validation/repairqfix.py
Tare/validation/stringfycode.py
Tare-0.0.4.dist-info/METADATA
Tare-0.0.4.dist-info/WHEEL
Tare-0.0.4.dist-info/top_level.txt
Tare-0.0.4.dist-info/RECORD
